fuzzytime/__init__.py
fuzzytime/helper.py
fuzzytime-1.1.dist-info/DESCRIPTION.rst
fuzzytime-1.1.dist-info/METADATA
fuzzytime-1.1.dist-info/RECORD
fuzzytime-1.1.dist-info/WHEEL
fuzzytime-1.1.dist-info/metadata.json
fuzzytime-1.1.dist-info/top_level.txt
