Metadata-Version: 2.0
Name: fuzzytime
Version: 1.1
Summary: Turns input datetime into fuzzy timestamp format
Home-page: https://github.com/harshildp/fuzzytime
Author: Harshil P.
Author-email: harshilp@uw.edu
License: UNKNOWN
Keywords: date time datetime timeago fuzzy
Platform: UNKNOWN
